[[{"session_id":303693169,"subsession_id":84317974,"start_time":"2026-03-19T01:45:00Z","end_time":"2026-03-19T02:27:22Z","license_category_id":5,"license_category":"Sports Car","num_drivers":23,"num_cautions":0,"num_caution_laps":0,"num_lead_changes":0,"event_average_lap":1232743,"event_best_lap_time":1220337,"event_laps_complete":13,"driver_changes":false,"winner_group_id":1423296,"winner_name":"Santiago Borrego","winner_ai":false,"cust_id":924869,"starting_position":18,"finish_position":12,"starting_position_in_class":18,"finish_position_in_class":12,"laps_complete":13,"laps_led":0,"incidents":10,"car_class_id":4093,"car_id":208,"car_class_name":"Porsche 911 Cup (992.2)","car_class_short_name":"Porsche 992.2","car_name":"Porsche 911 Cup (992.2)","car_name_abbreviated":"P9922","track":{"config_name":"International","track_id":95,"track_name":"Sebring International Raceway"},"official_session":true,"season_id":6110,"season_year":2026,"season_quarter":2,"event_type":5,"event_type_name":"Race","series_id":299,"series_name":"iRacing Porsche Cup by CONSPIT","series_short_name":"iRacing Porsche Cup by CONSPIT","race_week_num":0,"event_strength_of_field":1910,"champ_points":54,"drop_race":true,"season_license_group":3,"season_license_group_name":"Class C"},{"session_id":303909510,"subsession_id":84368693,"start_time":"2026-03-21T02:45:00Z","end_time":"2026-03-21T03:26:53Z","license_category_id":5,"license_category":"Sports Car","num_drivers":23,"num_cautions":0,"num_caution_laps":0,"num_lead_changes":2,"event_average_lap":1231111,"event_best_lap_time":1213049,"event_laps_complete":13,"driver_changes":false,"winner_group_id":434516,"winner_name":"Cody Seegert","winner_ai":false,"cust_id":924869,"starting_position":15,"finish_position":20,"starting_position_in_class":15,"finish_position_in_class":20,"laps_complete":5,"laps_led":0,"incidents":2,"car_class_id":4093,"car_id":208,"car_class_name":"Porsche 911 Cup (992.2)","car_class_short_name":"Porsche 992.2","car_name":"Porsche 911 Cup (992.2)","car_name_abbreviated":"P9922","track":{"config_name":"International","track_id":95,"track_name":"Sebring International Raceway"},"official_session":true,"season_id":6111,"season_year":2026,"season_quarter":2,"event_type":5,"event_type_name":"Race","series_id":476,"series_name":"iRacing Porsche Cup - Fixed by CONSPIT","series_short_name":"iRacing Porsche Cup - Fixed by CONSPIT","race_week_num":0,"event_strength_of_field":1870,"champ_points":15,"drop_race":true,"season_license_group":3,"season_license_group_name":"Class C"},{"session_id":303914018,"subsession_id":84369876,"start_time":"2026-03-21T03:45:00Z","end_time":"2026-03-21T04:27:52Z","license_category_id":5,"license_category":"Sports Car","num_drivers":24,"num_cautions":0,"num_caution_laps":0,"num_lead_changes":1,"event_average_lap":1234515,"event_best_lap_time":1220813,"event_laps_complete":13,"driver_changes":false,"winner_group_id":51445,"winner_name":"Aleksandr Potapov","winner_ai":false,"cust_id":924869,"starting_position":23,"finish_position":7,"starting_position_in_class":23,"finish_position_in_class":7,"laps_complete":13,"laps_led":0,"incidents":4,"car_class_id":4093,"car_id":208,"car_class_name":"Porsche 911 Cup (992.2)","car_class_short_name":"Porsche 992.2","car_name":"Porsche 911 Cup (992.2)","car_name_abbreviated":"P9922","track":{"config_name":"International","track_id":95,"track_name":"Sebring International Raceway"},"official_session":true,"season_id":6110,"season_year":2026,"season_quarter":2,"event_type":5,"event_type_name":"Race","series_id":299,"series_name":"iRacing Porsche Cup by CONSPIT","series_short_name":"iRacing Porsche Cup by CONSPIT","race_week_num":0,"event_strength_of_field":2044,"champ_points":88,"drop_race":true,"season_license_group":3,"season_license_group_name":"Class C"},{"session_id":303988943,"subsession_id":84388323,"start_time":"2026-03-21T20:45:00Z","end_time":"2026-03-21T21:27:01Z","license_category_id":5,"license_category":"Sports Car","num_drivers":24,"num_cautions":0,"num_caution_laps":0,"num_lead_changes":0,"event_average_lap":1226919,"event_best_lap_time":1214120,"event_laps_complete":13,"driver_changes":false,"winner_group_id":1201090,"winner_name":"Martijn Goertz","winner_ai":false,"cust_id":924869,"starting_position":18,"finish_position":14,"starting_position_in_class":18,"finish_position_in_class":14,"laps_complete":13,"laps_led":0,"incidents":11,"car_class_id":4093,"car_id":208,"car_class_name":"Porsche 911 Cup (992.2)","car_class_short_name":"Porsche 992.2","car_name":"Porsche 911 Cup (992.2)","car_name_abbreviated":"P9922","track":{"config_name":"International","track_id":95,"track_name":"Sebring International Raceway"},"official_session":true,"season_id":6111,"season_year":2026,"season_quarter":2,"event_type":5,"event_type_name":"Race","series_id":476,"series_name":"iRacing Porsche Cup - Fixed by CONSPIT","series_short_name":"iRacing Porsche Cup - Fixed by CONSPIT","race_week_num":0,"event_strength_of_field":1895,"champ_points":46,"drop_race":false,"season_license_group":3,"season_license_group_name":"Class C"},{"session_id":304015754,"subsession_id":84395712,"start_time":"2026-03-22T02:45:00Z","end_time":"2026-03-22T03:26:37Z","license_category_id":5,"license_category":"Sports Car","num_drivers":24,"num_cautions":0,"num_caution_laps":0,"num_lead_changes":0,"event_average_lap":1231235,"event_best_lap_time":1212640,"event_laps_complete":13,"driver_changes":false,"winner_group_id":1028977,"winner_name":"Glenn Del Castillo","winner_ai":false,"cust_id":924869,"starting_position":23,"finish_position":23,"starting_position_in_class":23,"finish_position_in_class":23,"laps_complete":1,"laps_led":0,"incidents":6,"car_class_id":4093,"car_id":208,"car_class_name":"Porsche 911 Cup (992.2)","car_class_short_name":"Porsche 992.2","car_name":"Porsche 911 Cup (992.2)","car_name_abbreviated":"P9922","track":{"config_name":"International","track_id":95,"track_name":"Sebring International Raceway"},"official_session":true,"season_id":6111,"season_year":2026,"season_quarter":2,"event_type":5,"event_type_name":"Race","series_id":476,"series_name":"iRacing Porsche Cup - Fixed by CONSPIT","series_short_name":"iRacing Porsche Cup - Fixed by CONSPIT","race_week_num":0,"event_strength_of_field":2063,"champ_points":2,"drop_race":true,"season_license_group":3,"season_license_group_name":"Class C"},{"session_id":304024693,"subsession_id":84397951,"start_time":"2026-03-22T04:45:00Z","end_time":"2026-03-22T05:27:42Z","license_category_id":5,"license_category":"Sports Car","num_drivers":23,"num_cautions":0,"num_caution_laps":0,"num_lead_changes":0,"event_average_lap":1228742,"event_best_lap_time":1213515,"event_laps_complete":13,"driver_changes":false,"winner_group_id":1135885,"winner_name":"Kanglong Cheng","winner_ai":false,"cust_id":924869,"starting_position":2,"finish_position":2,"starting_position_in_class":2,"finish_position_in_class":2,"laps_complete":13,"laps_led":0,"incidents":4,"car_class_id":4093,"car_id":208,"car_class_name":"Porsche 911 Cup (992.2)","car_class_short_name":"Porsche 992.2","car_name":"Porsche 911 Cup (992.2)","car_name_abbreviated":"P9922","track":{"config_name":"International","track_id":95,"track_name":"Sebring International Raceway"},"official_session":true,"season_id":6111,"season_year":2026,"season_quarter":2,"event_type":5,"event_type_name":"Race","series_id":476,"series_name":"iRacing Porsche Cup - Fixed by CONSPIT","series_short_name":"iRacing Porsche Cup - Fixed by CONSPIT","race_week_num":0,"event_strength_of_field":1781,"champ_points":100,"drop_race":false,"season_license_group":3,"season_license_group_name":"Class C"},{"session_id":304122316,"subsession_id":84423950,"start_time":"2026-03-23T02:45:00Z","end_time":"2026-03-23T03:27:27Z","license_category_id":5,"license_category":"Sports Car","num_drivers":22,"num_cautions":0,"num_caution_laps":0,"num_lead_changes":1,"event_average_lap":1231008,"event_best_lap_time":1215561,"event_laps_complete":13,"driver_changes":false,"winner_group_id":525230,"winner_name":"Norberto Boleo","winner_ai":false,"cust_id":924869,"starting_position":16,"finish_position":19,"starting_position_in_class":16,"finish_position_in_class":19,"laps_complete":8,"laps_led":0,"incidents":7,"car_class_id":4093,"car_id":208,"car_class_name":"Porsche 911 Cup (992.2)","car_class_short_name":"Porsche 992.2","car_name":"Porsche 911 Cup (992.2)","car_name_abbreviated":"P9922","track":{"config_name":"International","track_id":95,"track_name":"Sebring International Raceway"},"official_session":true,"season_id":6111,"season_year":2026,"season_quarter":2,"event_type":5,"event_type_name":"Race","series_id":476,"series_name":"iRacing Porsche Cup - Fixed by CONSPIT","series_short_name":"iRacing Porsche Cup - Fixed by CONSPIT","race_week_num":0,"event_strength_of_field":1999,"champ_points":16,"drop_race":true,"season_license_group":3,"season_license_group_name":"Class C"},{"session_id":304126779,"subsession_id":84424955,"start_time":"2026-03-23T03:45:00Z","end_time":"2026-03-23T04:27:46Z","license_category_id":5,"license_category":"Sports Car","num_drivers":24,"num_cautions":0,"num_caution_laps":0,"num_lead_changes":1,"event_average_lap":1234972,"event_best_lap_time":1218244,"event_laps_complete":13,"driver_changes":false,"winner_group_id":1455544,"winner_name":"Titee Milker","winner_ai":false,"cust_id":924869,"starting_position":8,"finish_position":6,"starting_position_in_class":8,"finish_position_in_class":6,"laps_complete":13,"laps_led":0,"incidents":4,"car_class_id":4093,"car_id":208,"car_class_name":"Porsche 911 Cup (992.2)","car_class_short_name":"Porsche 992.2","car_name":"Porsche 911 Cup (992.2)","car_name_abbreviated":"P9922","track":{"config_name":"International","track_id":95,"track_name":"Sebring International Raceway"},"official_session":true,"season_id":6110,"season_year":2026,"season_quarter":2,"event_type":5,"event_type_name":"Race","series_id":299,"series_name":"iRacing Porsche Cup by CONSPIT","series_short_name":"iRacing Porsche Cup by CONSPIT","race_week_num":0,"event_strength_of_field":1958,"champ_points":90,"drop_race":false,"season_license_group":3,"season_license_group_name":"Class C"},{"session_id":304549096,"subsession_id":84526526,"start_time":"2026-03-27T03:30:00Z","end_time":"2026-03-27T04:20:36Z","license_category_id":5,"license_category":"Sports Car","num_drivers":31,"num_cautions":0,"num_caution_laps":0,"num_lead_changes":1,"event_average_lap":1152826,"event_best_lap_time":1133681,"event_laps_complete":16,"driver_changes":false,"winner_group_id":956107,"winner_name":"Alex Warkus","winner_ai":false,"cust_id":924869,"starting_position":27,"finish_position":22,"starting_position_in_class":14,"finish_position_in_class":12,"laps_complete":14,"laps_led":0,"incidents":7,"car_class_id":2268,"car_id":119,"car_class_name":"GT4 Class","car_class_short_name":"GT4 Class","car_name":"Porsche 718 Cayman GT4 Clubsport MR","car_name_abbreviated":"P718","track":{"config_name":"International","track_id":95,"track_name":"Sebring International Raceway"},"official_session":true,"season_id":6100,"season_year":2026,"season_quarter":2,"event_type":5,"event_type_name":"Race","series_id":502,"series_name":"Sports Car Challenge by Falken Tyre","series_short_name":"Sports Car Challenge by Falken Tyre","race_week_num":1,"event_strength_of_field":2439,"champ_points":42,"drop_race":true,"season_license_group":3,"season_license_group_name":"Class C"},{"session_id":304610375,"subsession_id":84539486,"start_time":"2026-03-27T17:30:00Z","end_time":"2026-03-27T18:21:21Z","license_category_id":5,"license_category":"Sports Car","num_drivers":40,"num_cautions":0,"num_caution_laps":0,"num_lead_changes":0,"event_average_lap":1157700,"event_best_lap_time":1142669,"event_laps_complete":16,"driver_changes":false,"winner_group_id":328982,"winner_name":"Quentin Guilbaud","winner_ai":false,"cust_id":924869,"starting_position":28,"finish_position":22,"starting_position_in_class":14,"finish_position_in_class":15,"laps_complete":14,"laps_led":0,"incidents":6,"car_class_id":2268,"car_id":119,"car_class_name":"GT4 Class","car_class_short_name":"GT4 Class","car_name":"Porsche 718 Cayman GT4 Clubsport MR","car_name_abbreviated":"P718","track":{"config_name":"International","track_id":95,"track_name":"Sebring International Raceway"},"official_session":true,"season_id":6100,"season_year":2026,"season_quarter":2,"event_type":5,"event_type_name":"Race","series_id":502,"series_name":"Sports Car Challenge by Falken Tyre","series_short_name":"Sports Car Challenge by Falken Tyre","race_week_num":1,"event_strength_of_field":1875,"champ_points":45,"drop_race":true,"season_license_group":3,"season_license_group_name":"Class C"},{"session_id":304628198,"subsession_id":84544404,"start_time":"2026-03-27T21:30:00Z","end_time":"2026-03-27T22:21:51Z","license_category_id":5,"license_category":"Sports Car","num_drivers":37,"num_cautions":0,"num_caution_laps":0,"num_lead_changes":0,"event_average_lap":1169831,"event_best_lap_time":1140041,"event_laps_complete":16,"driver_changes":false,"winner_group_id":429594,"winner_name":"Cole Gamma","winner_ai":false,"cust_id":924869,"starting_position":33,"finish_position":31,"starting_position_in_class":20,"finish_position_in_class":18,"laps_complete":7,"laps_led":0,"incidents":6,"car_class_id":2268,"car_id":119,"car_class_name":"GT4 Class","car_class_short_name":"GT4 Class","car_name":"Porsche 718 Cayman GT4 Clubsport MR","car_name_abbreviated":"P718","track":{"config_name":"International","track_id":95,"track_name":"Sebring International Raceway"},"official_session":true,"season_id":6100,"season_year":2026,"season_quarter":2,"event_type":5,"event_type_name":"Race","series_id":502,"series_name":"Sports Car Challenge by Falken Tyre","series_short_name":"Sports Car Challenge by Falken Tyre","race_week_num":1,"event_strength_of_field":1844,"champ_points":24,"drop_race":true,"season_license_group":3,"season_license_group_name":"Class C"},{"session_id":304637178,"subsession_id":84546887,"start_time":"2026-03-27T23:30:00Z","end_time":"2026-03-28T00:21:35Z","license_category_id":5,"license_category":"Sports Car","num_drivers":36,"num_cautions":0,"num_caution_laps":0,"num_lead_changes":0,"event_average_lap":1167965,"event_best_lap_time":1147538,"event_laps_complete":16,"driver_changes":false,"winner_group_id":257854,"winner_name":"John Tomin","winner_ai":false,"cust_id":924869,"starting_position":24,"finish_position":19,"starting_position_in_class":12,"finish_position_in_class":11,"laps_complete":14,"laps_led":0,"incidents":5,"car_class_id":2268,"car_id":119,"car_class_name":"GT4 Class","car_class_short_name":"GT4 Class","car_name":"Porsche 718 Cayman GT4 Clubsport MR","car_name_abbreviated":"P718","track":{"config_name":"International","track_id":95,"track_name":"Sebring International Raceway"},"official_session":true,"season_id":6100,"season_year":2026,"season_quarter":2,"event_type":5,"event_type_name":"Race","series_id":502,"series_name":"Sports Car Challenge by Falken Tyre","series_short_name":"Sports Car Challenge by Falken Tyre","race_week_num":1,"event_strength_of_field":1723,"champ_points":53,"drop_race":false,"season_license_group":3,"season_license_group_name":"Class C"},{"session_id":304657513,"subsession_id":84552498,"start_time":"2026-03-28T04:00:00Z","end_time":"2026-03-28T06:22:04Z","license_category_id":5,"license_category":"Sports Car","num_drivers":38,"num_cautions":0,"num_caution_laps":0,"num_lead_changes":6,"event_average_lap":1340452,"event_best_lap_time":1309190,"event_laps_complete":54,"driver_changes":false,"winner_group_id":1005415,"winner_name":"Adrian Martin Exposito","winner_ai":false,"cust_id":924869,"starting_position":23,"finish_position":14,"starting_position_in_class":23,"finish_position_in_class":9,"laps_complete":54,"laps_led":0,"incidents":13,"car_class_id":2268,"car_id":119,"car_class_name":"GT4 Class","car_class_short_name":"GT4 Class","car_name":"Porsche 718 Cayman GT4 Clubsport MR","car_name_abbreviated":"P718","track":{"config_name":"International","track_id":95,"track_name":"Sebring International Raceway"},"official_session":true,"season_id":6102,"season_year":2026,"season_quarter":2,"event_type":5,"event_type_name":"Race","series_id":492,"series_name":"IMSA Michelin Pilot Challenge Series","series_short_name":"IMSA Michelin Pilot Challenge Series","race_week_num":0,"event_strength_of_field":1902,"champ_points":72,"drop_race":false,"season_license_group":3,"season_license_group_name":"Class C"},{"session_id":304761883,"subsession_id":84578237,"start_time":"2026-03-29T03:30:00Z","end_time":"2026-03-29T04:20:16Z","license_category_id":5,"license_category":"Sports Car","num_drivers":40,"num_cautions":0,"num_caution_laps":0,"num_lead_changes":0,"event_average_lap":1146305,"event_best_lap_time":1128336,"event_laps_complete":16,"driver_changes":false,"winner_group_id":755414,"winner_name":"Mobin Khan","winner_ai":false,"cust_id":924869,"starting_position":25,"finish_position":18,"starting_position_in_class":11,"finish_position_in_class":9,"laps_complete":14,"laps_led":0,"incidents":8,"car_class_id":2268,"car_id":119,"car_class_name":"GT4 Class","car_class_short_name":"GT4 Class","car_name":"Porsche 718 Cayman GT4 Clubsport MR","car_name_abbreviated":"P718","track":{"config_name":"International","track_id":95,"track_name":"Sebring International Raceway"},"official_session":true,"season_id":6100,"season_year":2026,"season_quarter":2,"event_type":5,"event_type_name":"Race","series_id":502,"series_name":"Sports Car Challenge by Falken Tyre","series_short_name":"Sports Car Challenge by Falken Tyre","race_week_num":1,"event_strength_of_field":2463,"champ_points":90,"drop_race":false,"season_license_group":3,"season_license_group_name":"Class C"},{"session_id":304859345,"subsession_id":84602699,"start_time":"2026-03-30T01:30:00Z","end_time":"2026-03-30T02:21:33Z","license_category_id":5,"license_category":"Sports Car","num_drivers":36,"num_cautions":0,"num_caution_laps":0,"num_lead_changes":0,"event_average_lap":1171200,"event_best_lap_time":1149793,"event_laps_complete":16,"driver_changes":false,"winner_group_id":1230947,"winner_name":"Tyler Grenier2","winner_ai":false,"cust_id":924869,"starting_position":6,"finish_position":8,"starting_position_in_class":6,"finish_position_in_class":8,"laps_complete":16,"laps_led":0,"incidents":12,"car_class_id":4018,"car_id":165,"car_class_name":"Ligier JS P320","car_class_short_name":"Ligier JS P320","car_name":"Ligier JS P320","car_name_abbreviated":"LJSP","track":{"config_name":"International","track_id":95,"track_name":"Sebring International Raceway"},"official_session":true,"season_id":6100,"season_year":2026,"season_quarter":2,"event_type":5,"event_type_name":"Race","series_id":502,"series_name":"Sports Car Challenge by Falken Tyre","series_short_name":"Sports Car Challenge by Falken Tyre","race_week_num":1,"event_strength_of_field":1636,"champ_points":35,"drop_race":false,"season_license_group":3,"season_license_group_name":"Class C"}]]